pyasn1_modules/__init__.py
pyasn1_modules/pem.py
pyasn1_modules/rfc1155.py
pyasn1_modules/rfc1157.py
pyasn1_modules/rfc1901.py
pyasn1_modules/rfc1902.py
pyasn1_modules/rfc1905.py
pyasn1_modules/rfc2251.py
pyasn1_modules/rfc2314.py
pyasn1_modules/rfc2315.py
pyasn1_modules/rfc2437.py
pyasn1_modules/rfc2459.py
pyasn1_modules/rfc2511.py
pyasn1_modules/rfc2560.py
pyasn1_modules/rfc2631.py
pyasn1_modules/rfc2634.py
pyasn1_modules/rfc2876.py
pyasn1_modules/rfc2985.py
pyasn1_modules/rfc2986.py
pyasn1_modules/rfc3058.py
pyasn1_modules/rfc3114.py
pyasn1_modules/rfc3125.py
pyasn1_modules/rfc3161.py
pyasn1_modules/rfc3274.py
pyasn1_modules/rfc3279.py
pyasn1_modules/rfc3280.py
pyasn1_modules/rfc3281.py
pyasn1_modules/rfc3370.py
pyasn1_modules/rfc3412.py
pyasn1_modules/rfc3414.py
pyasn1_modules/rfc3447.py
pyasn1_modules/rfc3537.py
pyasn1_modules/rfc3560.py
pyasn1_modules/rfc3565.py
pyasn1_modules/rfc3657.py
pyasn1_modules/rfc3709.py
pyasn1_modules/rfc3739.py
pyasn1_modules/rfc3770.py
pyasn1_modules/rfc3779.py
pyasn1_modules/rfc3820.py
pyasn1_modules/rfc3852.py
pyasn1_modules/rfc4010.py
pyasn1_modules/rfc4043.py
pyasn1_modules/rfc4055.py
pyasn1_modules/rfc4073.py
pyasn1_modules/rfc4108.py
pyasn1_modules/rfc4210.py
pyasn1_modules/rfc4211.py
pyasn1_modules/rfc4334.py
pyasn1_modules/rfc4357.py
pyasn1_modules/rfc4387.py
pyasn1_modules/rfc4476.py
pyasn1_modules/rfc4490.py
pyasn1_modules/rfc4491.py
pyasn1_modules/rfc4683.py
pyasn1_modules/rfc4985.py
pyasn1_modules/rfc5035.py
pyasn1_modules/rfc5083.py
pyasn1_modules/rfc5084.py
pyasn1_modules/rfc5126.py
pyasn1_modules/rfc5208.py
pyasn1_modules/rfc5275.py
pyasn1_modules/rfc5280.py
pyasn1_modules/rfc5480.py
pyasn1_modules/rfc5636.py
pyasn1_modules/rfc5639.py
pyasn1_modules/rfc5649.py
pyasn1_modules/rfc5652.py
pyasn1_modules/rfc5697.py
pyasn1_modules/rfc5751.py
pyasn1_modules/rfc5752.py
pyasn1_modules/rfc5753.py
pyasn1_modules/rfc5755.py
pyasn1_modules/rfc5913.py
pyasn1_modules/rfc5914.py
pyasn1_modules/rfc5915.py
pyasn1_modules/rfc5916.py
pyasn1_modules_lextudio-0.2.9.dist-info/LICENSE.txt
pyasn1_modules_lextudio-0.2.9.dist-info/WHEEL
pyasn1_modules_lextudio-0.2.9.dist-info/METADATA
pyasn1_modules_lextudio-0.2.9.dist-info/RECORD
